gedcomx/TopLevelTypeCollection.py
gedcomx/__init__.py
gedcomx/_gedcom5x.py
gedcomx/address.py
gedcomx/agent.py
gedcomx/attribution.py
gedcomx/conclusion.py
gedcomx/convertion.py
gedcomx/coverage.py
gedcomx/date.py
gedcomx/document.py
gedcomx/event.py
gedcomx/evidence_reference.py
gedcomx/exceptions.py
gedcomx/extensible.py
gedcomx/extensible_enum.py
gedcomx/fact.py
gedcomx/gedcom.py
gedcomx/gedcomx.py
gedcomx/gender.py
gedcomx/group.py
gedcomx/identifier.py
gedcomx/logging_hub.py
gedcomx/mutations.py
gedcomx/name.py
gedcomx/note.py
gedcomx/online_account.py
gedcomx/person.py
gedcomx/place_description.py
gedcomx/place_reference.py
gedcomx/qualifier.py
gedcomx/relationship.py
gedcomx/resource.py
gedcomx/schemas.py
gedcomx/serialization.py
gedcomx/source_citation.py
gedcomx/source_description.py
gedcomx/source_reference.py
gedcomx/subject.py
gedcomx/textvalue.py
gedcomx/translation.py
gedcomx/uri.py
gedcomx/zip.py
gedcomx/extensions/__init__.py
gedcomx/gedcom7/Exceptions.py
gedcomx/gedcom7/GedcomStructure.py
gedcomx/gedcom7/__init__.py
gedcomx/gedcom7/g7interop.py
gedcomx/gedcom7/gedcom7.py
gedcomx/gedcom7/logger.py
gedcomx/gedcom7/specification.py
gedcom_x-0.5.15.dist-info/METADATA
gedcom_x-0.5.15.dist-info/WHEEL
gedcom_x-0.5.15.dist-info/top_level.txt
gedcom_x-0.5.15.dist-info/RECORD
