Metadata-Version: 2.4
Name: gedcom-x
Version: 0.5.15
Summary: Python implimentation of gedcom-x standard
Author-email: "David J. Cartwright" <davidcartwright@hotmail.com>
License: MIT
Project-URL: Documentation, https://readthedocs.org/projects/gedcom-x/
Keywords: gedcom,gedcomx,ged
Classifier: Development Status :: 3 - Alpha
Classifier: Programming Language :: Python :: 3
Classifier: Environment :: Console
Classifier: License :: OSI Approved :: MIT License
Classifier: Operating System :: OS Independent
Classifier: Topic :: Utilities
Classifier: Topic :: Software Development :: User Interfaces
Requires-Python: >=3.6
Requires-Dist: python-dateutil
Requires-Dist: orjson
Dynamic: requires-python
